kokoro_tts_tool/__init__.py
kokoro_tts_tool/cli.py
kokoro_tts_tool/completion.py
kokoro_tts_tool/engine.py
kokoro_tts_tool/logging_config.py
kokoro_tts_tool/models.py
kokoro_tts_tool/splitter.py
kokoro_tts_tool/streaming.py
kokoro_tts_tool/utils.py
kokoro_tts_tool/voices.py
kokoro_tts_tool/commands/__init__.py
kokoro_tts_tool/commands/infinite_commands.py
kokoro_tts_tool/commands/info_commands.py
kokoro_tts_tool/commands/init_commands.py
kokoro_tts_tool/commands/synthesize_commands.py
kokoro_tts_tool/commands/voice_commands.py
kokoro_tts_tool-0.1.0.dist-info/METADATA
kokoro_tts_tool-0.1.0.dist-info/WHEEL
kokoro_tts_tool-0.1.0.dist-info/entry_points.txt
kokoro_tts_tool-0.1.0.dist-info/licenses/LICENSE
kokoro_tts_tool-0.1.0.dist-info/RECORD
