Metadata-Version: 2.4
Name: kokoro-tts-tool
Version: 0.1.0
Summary: A CLI that provides local text-to-speech using Kokoro TTS on Apple Silicon
Project-URL: Homepage, https://github.com/dnvriend/kokoro-tts-tool
Project-URL: Repository, https://github.com/dnvriend/kokoro-tts-tool
Project-URL: Issues, https://github.com/dnvriend/kokoro-tts-tool/issues
Author-email: Dennis Vriend <dvriend@ilionx.com>
License: MIT
License-File: LICENSE
Keywords: cli,tool
Classifier: Development Status :: 4 - Beta
Classifier: Intended Audience :: Developers
Classifier: License :: OSI Approved :: MIT License
Classifier: Programming Language :: Python :: 3
Classifier: Programming Language :: Python :: 3.13
Requires-Python: >=3.13
Requires-Dist: click>=8.1.7
Requires-Dist: kokoro-onnx>=0.4.9
Requires-Dist: langchain-text-splitters>=0.3.0
Requires-Dist: numpy>=2.0.2
Requires-Dist: sounddevice>=0.5.1
Requires-Dist: soundfile>=0.13.1
